setuptools_grpc/__init__.py
setuptools_grpc/_utils.py
setuptools_grpc/build_backend.py
setuptools_grpc/build_grpc.py
setuptools_grpc-1.0.0.dist-info/licenses/LICENSE
setuptools_grpc-1.0.0.dist-info/METADATA
setuptools_grpc-1.0.0.dist-info/WHEEL
setuptools_grpc-1.0.0.dist-info/entry_points.txt
setuptools_grpc-1.0.0.dist-info/top_level.txt
setuptools_grpc-1.0.0.dist-info/RECORD
