Metadata-Version: 2.4
Name: setuptools-grpc
Version: 1.0.0
Summary: Plugin for setuptools and grpc / protobuf python module build
Home-page: https://github.com/CZ-NIC/setuptools-grpc
Author: Jan Musílek
Author-email: jan.musilek@nic.cz
License: GPLv3+
Classifier: Development Status :: 5 - Production/Stable
Classifier: Intended Audience :: Developers
Classifier: License :: OSI Approved :: GNU General Public License v3 or later (GPLv3+)
Classifier: Operating System :: OS Independent
Classifier: Programming Language :: Python
Classifier: Programming Language :: Python :: 3.9
Classifier: Programming Language :: Python :: 3.10
Classifier: Programming Language :: Python :: 3.11
Classifier: Programming Language :: Python :: 3.12
Classifier: Programming Language :: Python :: 3.13
Classifier: Topic :: Software Development :: Build Tools
Requires-Python: ~=3.9
License-File: LICENSE
Requires-Dist: setuptools
Requires-Dist: grpcio-tools>=1.49
Provides-Extra: quality
Requires-Dist: doc8; extra == "quality"
Requires-Dist: ruff; extra == "quality"
Provides-Extra: test
Requires-Dist: build; extra == "test"
Requires-Dist: pytest; extra == "test"
Requires-Dist: pytest-cov; extra == "test"
Requires-Dist: testfixtures; extra == "test"
Requires-Dist: wheel; extra == "test"
Requires-Dist: wheel-inspect; extra == "test"
Dynamic: license-file
